firewheel_repo_base/__init__.py
firewheel_repo_base/base_graph_objects/base_objects/MANIFEST
firewheel_repo_base/base_graph_objects/base_objects/README.rst
firewheel_repo_base/base_graph_objects/base_objects/model_component_objects.py
firewheel_repo_base/base_graph_objects/generic_vm_objects/MANIFEST
firewheel_repo_base/base_graph_objects/generic_vm_objects/README.rst
firewheel_repo_base/base_graph_objects/generic_vm_objects/model_component_objects.py
firewheel_repo_base/blank_graph/MANIFEST
firewheel_repo_base/blank_graph/README.rst
firewheel_repo_base/blank_graph/plugin.py
firewheel_repo_base/common/as_checker/MANIFEST
firewheel_repo_base/common/as_checker/README.rst
firewheel_repo_base/common/as_checker/plugin.py
firewheel_repo_base/common/dropper/MANIFEST
firewheel_repo_base/common/dropper/README.rst
firewheel_repo_base/common/dropper/dropper.py
firewheel_repo_base/common/dropper/plugin.py
firewheel_repo_base/common/runner/MANIFEST
firewheel_repo_base/common/runner/README.rst
firewheel_repo_base/common/runner/plugin.py
firewheel_repo_base/common/runner/runner.py
firewheel_repo_base/control_network/MANIFEST
firewheel_repo_base/control_network/README.rst
firewheel_repo_base/control_network/plugin.py
firewheel_repo_base/minimega/configure_ips/MANIFEST
firewheel_repo_base/minimega/configure_ips/README.rst
firewheel_repo_base/minimega/configure_ips/plugin.py
firewheel_repo_base/minimega/create_mac_addrs/MANIFEST
firewheel_repo_base/minimega/create_mac_addrs/README.rst
firewheel_repo_base/minimega/create_mac_addrs/plugin.py
firewheel_repo_base/minimega/emulated_entities/MANIFEST
firewheel_repo_base/minimega/emulated_entities/README.rst
firewheel_repo_base/minimega/emulated_entities/model_component_objects.py
firewheel_repo_base/minimega/launch/MANIFEST
firewheel_repo_base/minimega/launch/README.rst
firewheel_repo_base/minimega/parse_experiment_graph/MANIFEST
firewheel_repo_base/minimega/parse_experiment_graph/README.rst
firewheel_repo_base-2.7.0.dist-info/LICENSE
firewheel_repo_base-2.7.0.dist-info/METADATA
firewheel_repo_base-2.7.0.dist-info/WHEEL
firewheel_repo_base-2.7.0.dist-info/entry_points.txt
firewheel_repo_base-2.7.0.dist-info/top_level.txt
firewheel_repo_base-2.7.0.dist-info/RECORD
